cex_clients/__init__.py
cex_clients/exceptions.py
cex_clients/loader.py
cex_clients/rs.py
cex_clients/binance/binance_async.py
cex_clients/binance/earn_api.py
cex_clients/binance/sapi.py
cex_clients/binance/web.py
cex_clients/binance/web_c2c.py
cex_clients/bybit/web_earn.py
cex_clients/bybit/web_p2p.py
cex_clients/commex/api.py
cex_clients/gate/premarket.py
cex_clients/htx/web.py
cex_clients/htx/web_c2c.py
cex_clients/kucoin/web.py
cex_clients/okx/web.py
cex_clients/wallet/pyro.py
cex_clients/wallet/web.py
cex_clients-0.1.2.dist-info/METADATA
cex_clients-0.1.2.dist-info/WHEEL
cex_clients-0.1.2.dist-info/top_level.txt
cex_clients-0.1.2.dist-info/RECORD
