Metadata-Version: 2.1
Name: cex-clients
Version: 0.1.2
Author-email: Mike Artemiev <mixartemev@gmail.com>
Project-URL: Homepage, https://gitlab.com/xync/back/cex-clients
Project-URL: Repository, https://gitlab.com/xync/back/cex-clients
Requires-Python: >=3.11
Requires-Dist: http-client-async
Requires-Dist: python-dotenv
Requires-Dist: asynchuobi
Requires-Dist: python-binance
Requires-Dist: pybit
Requires-Dist: python-okx
Requires-Dist: xync-schema
